pso/__init__.py
pso/optimizer.py
pso/particle.py
pso2keras-1.0.5.1.dist-info/LICENSE
pso2keras-1.0.5.1.dist-info/METADATA
pso2keras-1.0.5.1.dist-info/WHEEL
pso2keras-1.0.5.1.dist-info/top_level.txt
pso2keras-1.0.5.1.dist-info/RECORD
