Metadata-Version: 2.1
Name: pso2keras
Version: 1.0.5.1
Summary: Particle Swarm Optimization on tensorflow package
Home-page: https://github.com/jung-geun/PSO
Author: pieroot
Author-email: jgbong0306@gmail.com
License: MIT
Keywords: pso,tensorflow,keras,optimization,particle swarm optimization,pso2keras
Platform: UNKNOWN
Classifier: License :: OSI Approved :: MIT License
Classifier: Programming Language :: Python :: 3 :: Only
Classifier: Programming Language :: Python :: 3.8
Classifier: Programming Language :: Python :: 3.9
Classifier: Programming Language :: Python :: 3.10
Classifier: Programming Language :: Python :: 3.11
Requires-Python: >=3.8
License-File: LICENSE
Requires-Dist: tqdm
Requires-Dist: numpy
Requires-Dist: pandas
Requires-Dist: ipython
Requires-Dist: matplotlib
Requires-Dist: tensorflow
Requires-Dist: keras
Requires-Dist: scikit-learn
Requires-Dist: tensorboard
